{
    "name": "gabecraft",
    "version": "0.1.0",
    "dependencies": [
        {
            "name": "daxa",
            "features": [
                "glslang",
                "utils"
            ]
        },
        "fmt",
        "glfw3",
        "glm",
        "stb",
        "nlohmann-json",
        "platform-folders",
        {
            "name": "imgui",
            "features": [
                "glfw-binding",
                "docking-experimental"
            ]
        }
    ],
    "builtin-baseline": "a1737683a6f8ec5d8673890581c2a8c55838d411",
    "overrides": [
        {
            "name": "daxa",
            "version-string": "nightly"
        }
    ]
}